grscheller/circular_array/__init__.py
grscheller/circular_array/ca.py
grscheller/circular_array/py.typed
grscheller_circular_array-3.8.1.dist-info/LICENSE
grscheller_circular_array-3.8.1.dist-info/WHEEL
grscheller_circular_array-3.8.1.dist-info/METADATA
grscheller_circular_array-3.8.1.dist-info/RECORD
