Metadata-Version: 2.3
Name: grscheller.circular-array
Version: 3.8.1
Summary: ### Circular Array
Keywords: circular array,circle array,CA,double ended queue,dequeue,dqueue,pop,push,popL,popR,pushL,pushR,indexable,auto-resizing,auto resizing,resizing
Author-email: "Geoffrey R. Scheller" <geoffrey@scheller.com>
Requires-Python: >=3.12
Classifier: Development Status :: 5 - Production/Stable
Classifier: Framework :: Pytest
Classifier: Intended Audience :: Developers
Classifier: License :: OSI Approved :: Apache Software License
Classifier: Operating System :: OS Independent
Classifier: Programming Language :: Python :: 3.13
Classifier: Typing :: Typed
Requires-Dist: pytest >=8.3.2 ; extra == "test"
Project-URL: Changelog, https://github.com/grscheller/circular-array/blob/main/CHANGELOG.md
Project-URL: Documentation, https://grscheller.github.io/grscheller-pypi-namespace-docs/circular-array
Project-URL: Source, https://github.com/grscheller/circular-array
Provides-Extra: test
